ansys/sound/core/__init__.py
ansys/sound/core/_pyansys_sound.py
ansys/sound/core/examples_helpers/__init__.py
ansys/sound/core/examples_helpers/download.py
ansys/sound/core/psychoacoustics/__init__.py
ansys/sound/core/psychoacoustics/_psychoacoustics_parent.py
ansys/sound/core/psychoacoustics/fluctuation_strength.py
ansys/sound/core/psychoacoustics/loudness_ansi_s3_4.py
ansys/sound/core/psychoacoustics/loudness_iso_532_1_stationary.py
ansys/sound/core/psychoacoustics/loudness_iso_532_1_time_varying.py
ansys/sound/core/psychoacoustics/loudness_iso_532_2.py
ansys/sound/core/psychoacoustics/prominence_ratio.py
ansys/sound/core/psychoacoustics/prominence_ratio_for_orders_over_time.py
ansys/sound/core/psychoacoustics/roughness.py
ansys/sound/core/psychoacoustics/sharpness.py
ansys/sound/core/psychoacoustics/sharpness_din_45692.py
ansys/sound/core/psychoacoustics/sharpness_din_45692_over_time.py
ansys/sound/core/psychoacoustics/sharpness_over_time.py
ansys/sound/core/psychoacoustics/spectral_centroid.py
ansys/sound/core/psychoacoustics/tonality_aures.py
ansys/sound/core/psychoacoustics/tonality_din_45681.py
ansys/sound/core/psychoacoustics/tonality_ecma_418_2.py
ansys/sound/core/psychoacoustics/tonality_iso_1996_2.py
ansys/sound/core/psychoacoustics/tonality_iso_1996_2_over_time.py
ansys/sound/core/psychoacoustics/tonality_iso_ts_20065.py
ansys/sound/core/psychoacoustics/tone_to_noise_ratio.py
ansys/sound/core/psychoacoustics/tone_to_noise_ratio_for_orders_over_time.py
ansys/sound/core/server_helpers/__init__.py
ansys/sound/core/server_helpers/_check_server_version.py
ansys/sound/core/server_helpers/_connect_to_or_start_server.py
ansys/sound/core/server_helpers/_validate_dpf_sound_connection.py
ansys/sound/core/signal_processing/__init__.py
ansys/sound/core/signal_processing/_signal_processing_parent.py
ansys/sound/core/signal_processing/filter.py
ansys/sound/core/signal_utilities/__init__.py
ansys/sound/core/signal_utilities/_signal_utilities_parent.py
ansys_sound_core-0.3.0.dist-info/licenses/LICENSE
ansys_sound_core-0.3.0.dist-info/WHEEL
ansys_sound_core-0.3.0.dist-info/METADATA
ansys_sound_core-0.3.0.dist-info/RECORD
