Metadata-Version: 2.4
Name: ansys-sound-core
Version: 0.3.0
Summary: A Python wrapper for Ansys DPF Sound.
Author-email: "ANSYS, Inc." <pyansys.core@ansys.com>
Maintainer-email: "ANSYS, Inc." <pyansys.core@ansys.com>
Requires-Python: >=3.10,<4
Classifier: Development Status :: 4 - Beta
Classifier: Programming Language :: Python :: 3.10
Classifier: Programming Language :: Python :: 3.11
Classifier: Programming Language :: Python :: 3.12
Classifier: Programming Language :: Python :: 3.13
Classifier: License :: OSI Approved :: MIT License
Classifier: Operating System :: OS Independent
License-File: LICENSE
Requires-Dist: ansys-dpf-core>=0.13.8,<1
Requires-Dist: matplotlib>=3.8.2,<4
Requires-Dist: platformdirs>=3.6.0
Requires-Dist: requests>=2.30.0
Requires-Dist: ansys-dpf-core==0.15.0 ; extra == "doc"
Requires-Dist: Sphinx==8.2.3 ; extra == "doc"
Requires-Dist: ansys-sphinx-theme==1.6.4 ; extra == "doc"
Requires-Dist: numpydoc==1.10.0 ; extra == "doc"
Requires-Dist: sphinx-autodoc-typehints==3.1.0 ; extra == "doc"
Requires-Dist: sphinx-copybutton==0.5.2 ; extra == "doc"
Requires-Dist: sphinx-gallery==0.20.0 ; extra == "doc"
Requires-Dist: sphinx-design==0.6.1 ; extra == "doc"
Requires-Dist: vtk==9.5.2 ; extra == "doc"
Requires-Dist: trame==3.12.0 ; extra == "doc"
Requires-Dist: trame_vtk==2.10.2 ; extra == "doc"
Requires-Dist: pyvista==0.46.4 ; extra == "doc"
Requires-Dist: pypandoc==1.16.2 ; extra == "doc"
Requires-Dist: jupyter-sphinx==0.5.3 ; extra == "doc"
Requires-Dist: sphinx-autobuild==2024.10.3 ; extra == "doc"
Requires-Dist: platformdirs==4.5.1 ; extra == "doc"
Requires-Dist: requests==2.32.5 ; extra == "doc"
Requires-Dist: scikit-learn==1.7.2 ; extra == "doc"
Requires-Dist: ansys-dpf-core==0.15.0 ; extra == "full"
Requires-Dist: matplotlib==3.10.8 ; extra == "full"
Requires-Dist: platformdirs==4.5.1 ; extra == "full"
Requires-Dist: requests==2.32.5 ; extra == "full"
Requires-Dist: scipy==1.15.3 ; extra == "full"
Requires-Dist: scikit-learn==1.7.2 ; extra == "full"
Requires-Dist: ansys-dpf-core==0.15.0 ; extra == "tests"
Requires-Dist: matplotlib==3.10.8 ; extra == "tests"
Requires-Dist: pytest==9.0.2 ; extra == "tests"
Requires-Dist: pytest-cov==7.0.0 ; extra == "tests"
Requires-Dist: pytest-dependency==0.6.0 ; extra == "tests"
Requires-Dist: platformdirs==4.5.1 ; extra == "tests"
Requires-Dist: regex==2025.11.3 ; extra == "tests"
Requires-Dist: requests==2.32.5 ; extra == "tests"
Requires-Dist: scipy==1.15.3 ; extra == "tests"
Provides-Extra: doc
Provides-Extra: full
Provides-Extra: tests
